{
  "posts": [
    {
      "id": 1,
      "author": 3012,
      "publishedAt": "2024-07-10T13:00:00Z",
      "title": "Everything Samsung Announced at Galaxy Unpacked in Paris",
      "description": "The long-awaited Galaxy Ring arrives alongside new folding smartphones, wireless earbuds, smartwatches, and a premium wearable that looks a lot like the Apple Watch Ultra.",
      "content": "It's a big day for Samsung. At its biannual Galaxy Unpacked eventheld today in Paris just weeks before the Olympics kickoffSamsung took the wraps off of eight new devices, one of which is an entirely… [+2113 chars]",
      "url": "https://www.wired.com/story/samsung-galaxy-unpacked-july-2024-flip6-fold6-galaxy-ring/",
      "imageUrl": "https://media.wired.com/photos/668da4a4f1cf59d7e4ba43af/191:100/w_1280,c_limit/Galaxy-Devices.jpg",
      "score": 794,
      "votes": [
        {
          "user": 0,
          "type": "downvote"
        },
        {
          "user": 2356,
          "type": "upvote"
        },
        {
          "user": 2223,
          "type": "upvote"
        },
        {
          "user": 2556,
          "type": "upvote"
        },
        {
          "user": 1825,
          "type": "upvote"
        },
        {
          "user": 637,
          "type": "upvote"
        },
        {
          "user": 3355,
          "type": "upvote"
        },
        {
          "user": 4100,
          "type": "upvote"
        },
        {
          "user": 1751,
          "type": "upvote"
        },
        {
          "user": 1386,
          "type": "upvote"
        },
        {
          "user": 874,
          "type": "upvote"
        },
        {
          "user": 1660,
          "type": "upvote"
        },
        {
          "user": 4513,
          "type": "upvote"
        },
        {
          "user": 2609,
          "type": "upvote"
        },
        {
          "user": 4147,
          "type": "upvote"
        },
        {
          "user": 4370,
          "type": "upvote"
        },
        {
          "user": 208,
          "type": "upvote"
        },
        {
          "user": 1885,
          "type": "upvote"
        },
        {
          "user": 3109,
          "type": "upvote"
        },
        {
          "user": 3694,
          "type": "upvote"
        },
        {
          "user": 624,
          "type": "upvote"
        },
        {
          "user": 2362,
          "type": "upvote"
        },
        {
          "user": 3455,
          "type": "upvote"
        },
        {
          "user": 4490,
          "type": "upvote"
        },
        {
          "user": 1887,
          "type": "upvote"
        },
        {
          "user": 2581,
          "type": "upvote"
        },
        {
          "user": 4055,
          "type": "upvote"
        },
        {
          "user": 2212,
          "type": "upvote"
        },
        {
          "user": 3234,
          "type": "upvote"
        },
        {
          "user": 3454,
          "type": "upvote"
        },
        {
          "user": 1493,
          "type": "upvote"
        },
        {
          "user": 395,
          "type": "upvote"
        },
        {
          "user": 338,
          "type": "upvote"
        },
        {
          "user": 2270,
          "type": "upvote"
        },
        {
          "user": 4371,
          "type": "upvote"
        },
        {
          "user": 1743,
          "type": "upvote"
        },
        {
          "user": 1083,
          "type": "upvote"
        },
        {
          "user": 3474,
          "type": "upvote"
        },
        {
          "user": 2515,
          "type": "upvote"
        },
        {
          "user": 2554,
          "type": "upvote"
        },
        {
          "user": 3710,
          "type": "upvote"
        },
        {
          "user": 4474,
          "type": "upvote"
        },
        {
          "user": 3094,
          "type": "upvote"
        },
        {
          "user": 3251,
          "type": "upvote"
        },
        {
          "user": 4211,
          "type": "upvote"
        },
        {
          "user": 3405,
          "type": "upvote"
        },
        {
          "user": 4043,
          "type": "upvote"
        },
        {
          "user": 377,
          "type": "upvote"
        },
        {
          "user": 1626,
          "type": "upvote"
        },
        {
          "user": 2256,
          "type": "upvote"
        },
        {
          "user": 1347,
          "type": "upvote"
        },
        {
          "user": 950,
          "type": "upvote"
        },
        {
          "user": 1030,
          "type": "upvote"
        },
        {
          "user": 4370,
          "type": "upvote"
        },
        {
          "user": 4629,
          "type": "upvote"
        },
        {
          "user": 4594,
          "type": "upvote"
        },
        {
          "user": 4667,
          "type": "upvote"
        },
        {
          "user": 1995,
          "type": "upvote"
        },
        {
          "user": 4334,
          "type": "upvote"
        },
        {
          "user": 369,
          "type": "upvote"
        },
        {
          "user": 3264,
          "type": "upvote"
        },
        {
          "user": 1818,
          "type": "upvote"
        },
        {
          "user": 4153,
          "type": "upvote"
        },
        {
          "user": 144,
          "type": "upvote"
        },
        {
          "user": 3339,
          "type": "upvote"
        },
        {
          "user": 1307,
          "type": "upvote"
        },
        {
          "user": 2760,
          "type": "upvote"
        },
        {
          "user": 1734,
          "type": "upvote"
        },
        {
          "user": 435,
          "type": "upvote"
        },
        {
          "user": 1189,
          "type": "upvote"
        },
        {
          "user": 4256,
          "type": "upvote"
        },
        {
          "user": 1891,
          "type": "upvote"
        },
        {
          "user": 1469,
          "type": "upvote"
        },
        {
          "user": 1531,
          "type": "upvote"
        },
        {
          "user": 1201,
          "type": "upvote"
        },
        {
          "user": 2164,
          "type": "upvote"
        },
        {
          "user": 30,
          "type": "upvote"
        },
        {
          "user": 251,
          "type": "upvote"
        },
        {
          "user": 2191,
          "type": "upvote"
        },
        {
          "user": 1810,
          "type": "upvote"
        },
        {
          "user": 3344,
          "type": "upvote"
        },
        {
          "user": 4532,
          "type": "upvote"
        },
        {
          "user": 1208,
          "type": "upvote"
        },
        {
          "user": 2070,
          "type": "upvote"
        },
        {
          "user": 605,
          "type": "upvote"
        },
        {
          "user": 488,
          "type": "upvote"
        },
        {
          "user": 2756,
          "type": "upvote"
        },
        {
          "user": 2865,
          "type": "upvote"
        },
        {
          "user": 4509,
          "type": "upvote"
        },
        {
          "user": 581,
          "type": "upvote"
        },
        {
          "user": 4585,
          "type": "upvote"
        },
        {
          "user": 4256,
          "type": "upvote"
        },
        {
          "user": 536,
          "type": "upvote"
        },
        {
          "user": 2184,
          "type": "upvote"
        },
        {
          "user": 4535,
          "type": "upvote"
        },
        {
          "user": 4012,
          "type": "upvote"
        },
        {
          "user": 447,
          "type": "upvote"
        },
        {
          "user": 4727,
          "type": "upvote"
        },
        {
          "user": 378,
          "type": "upvote"
        },
        {
          "user": 1221,
          "type": "upvote"
        },
        {
          "user": 2068,
          "type": "upvote"
        },
        {
          "user": 6,
          "type": "upvote"
        },
        {
          "user": 655,
          "type": "upvote"
        },
        {
          "user": 2853,
          "type": "upvote"
        },
        {
          "user": 2881,
          "type": "upvote"
        },
        {
          "user": 1258,
          "type": "upvote"
        },
        {
          "user": 1840,
          "type": "upvote"
        },
        {
          "user": 1143,
          "type": "upvote"
        },
        {
          "user": 2117,
          "type": "upvote"
        },
        {
          "user": 1942,
          "type": "upvote"
        },
        {
          "user": 3704,
          "type": "upvote"
        },
        {
          "user": 2593,
          "type": "upvote"
        },
        {
          "user": 414,
          "type": "upvote"
        },
        {
          "user": 1637,
          "type": "upvote"
        },
        {
          "user": 3140,
          "type": "upvote"
        },
        {
          "user": 626,
          "type": "upvote"
        },
        {
          "user": 3783,
          "type": "upvote"
        },
        {
          "user": 3021,
          "type": "upvote"
        },
        {
          "user": 2387,
          "type": "upvote"
        },
        {
          "user": 2016,
          "type": "upvote"
        },
        {
          "user": 367,
          "type": "upvote"
        },
        {
          "user": 1960,
          "type": "upvote"
        },
        {
          "user": 2211,
          "type": "upvote"
        },
        {
          "user": 1580,
          "type": "upvote"
        },
        {
          "user": 4691,
          "type": "upvote"
        },
        {
          "user": 2422,
          "type": "upvote"
        },
        {
          "user": 1391,
          "type": "upvote"
        },
        {
          "user": 111,
          "type": "upvote"
        },
        {
          "user": 1923,
          "type": "upvote"
        },
        {
          "user": 4762,
          "type": "upvote"
        },
        {
          "user": 2645,
          "type": "upvote"
        },
        {
          "user": 4163,
          "type": "upvote"
        },
        {
          "user": 1417,
          "type": "upvote"
        },
        {
          "user": 417,
          "type": "upvote"
        },
        {
          "user": 1548,
          "type": "upvote"
        },
        {
          "user": 4394,
          "type": "upvote"
        },
        {
          "user": 407,
          "type": "upvote"
        },
        {
          "user": 4311,
          "type": "upvote"
        },
        {
          "user": 1493,
          "type": "upvote"
        },
        {
          "user": 2120,
          "type": "upvote"
        },
        {
          "user": 3146,
          "type": "upvote"
        },
        {
          "user": 4806,
          "type": "upvote"
        },
        {
          "user": 1245,
          "type": "upvote"
        },
        {
          "user": 2259,
          "type": "upvote"
        },
        {
          "user": 142,
          "type": "upvote"
        },
        {
          "user": 2962,
          "type": "upvote"
        },
        {
          "user": 130,
          "type": "upvote"
        },
        {
          "user": 4489,
          "type": "upvote"
        },
        {
          "user": 3183,
          "type": "upvote"
        },
        {
          "user": 4542,
          "type": "upvote"
        },
        {
          "user": 2403,
          "type": "upvote"
        },
        {
          "user": 3194,
          "type": "upvote"
        },
        {
          "user": 4424,
          "type": "upvote"
        },
        {
          "user": 4664,
          "type": "upvote"
        },
        {
          "user": 358,
          "type": "upvote"
        },
        {
          "user": 4799,
          "type": "upvote"
        },
        {
          "user": 4911,
          "type": "upvote"
        },
        {
          "user": 3948,
          "type": "upvote"
        },
        {
          "user": 2014,
          "type": "upvote"
        },
        {
          "user": 2058,
          "type": "upvote"
        },
        {
          "user": 1316,
          "type": "upvote"
        },
        {
          "user": 4600,
          "type": "upvote"
        },
        {
          "user": 1348,
          "type": "upvote"
        },
        {
          "user": 2430,
          "type": "upvote"
        },
        {
          "user": 843,
          "type": "upvote"
        },
        {
          "user": 1544,
          "type": "upvote"
        },
        {
          "user": 498,
          "type": "upvote"
        },
        {
          "user": 498,
          "type": "upvote"
        },
        {
          "user": 3417,
          "type": "upvote"
        },
        {
          "user": 2050,
          "type": "upvote"
        },
        {
          "user": 922,
          "type": "upvote"
        },
        {
          "user": 4444,
          "type": "upvote"
        },
        {
          "user": 2245,
          "type": "upvote"
        },
        {
          "user": 625,
          "type": "upvote"
        },
        {
          "user": 1756,
          "type": "upvote"
        },
        {
          "user": 3670,
          "type": "upvote"
        },
        {
          "user": 2724,
          "type": "upvote"
        },
        {
          "user": 4815,
          "type": "upvote"
        },
        {
          "user": 3097,
          "type": "upvote"
        },
        {
          "user": 1513,
          "type": "upvote"
        },
        {
          "user": 367,
          "type": "upvote"
        },
        {
          "user": 735,
          "type": "upvote"
        },
        {
          "user": 2115,
          "type": "upvote"
        },
        {
          "user": 3095,
          "type": "upvote"
        },
        {
          "user": 3203,
          "type": "upvote"
        },
        {
          "user": 2860,
          "type": "upvote"
        },
        {
          "user": 73,
          "type": "upvote"
        },
        {
          "user": 4860,
          "type": "upvote"
        },
        {
          "user": 4506,
          "type": "upvote"
        },
        {
          "user": 3291,
          "type": "upvote"
        },
        {
          "user": 1942,
          "type": "upvote"
        },
        {
          "user": 1022,
          "type": "upvote"
        },
        {
          "user": 4324,
          "type": "upvote"
        },
        {
          "user": 4725,
          "type": "upvote"
        },
        {
          "user": 172,
          "type": "upvote"
        },
        {
          "user": 2641,
          "type": "upvote"
        },
        {
          "user": 1047,
          "type": "upvote"
        },
        {
          "user": 372,
          "type": "upvote"
        },
        {
          "user": 4029,
          "type": "upvote"
        },
        {
          "user": 4952,
          "type": "upvote"
        },
        {
          "user": 548,
          "type": "upvote"
        },
        {
          "user": 1328,
          "type": "upvote"
        },
        {
          "user": 2011,
          "type": "upvote"
        },
        {
          "user": 3157,
          "type": "upvote"
        },
        {
          "user": 651,
          "type": "upvote"
        },
        {
          "user": 3028,
          "type": "upvote"
        },
        {
          "user": 1739,
          "type": "upvote"
        },
        {
          "user": 4727,
          "type": "upvote"
        },
        {
          "user": 494,
          "type": "upvote"
        },
        {
          "user": 593,
          "type": "upvote"
        },
        {
          "user": 4977,
          "type": "upvote"
        },
        {
          "user": 2941,
          "type": "upvote"
        },
        {
          "user": 4756,
          "type": "upvote"
        },
        {
          "user": 427,
          "type": "upvote"
        },
        {
          "user": 3019,
          "type": "upvote"
        },
        {
          "user": 4294,
          "type": "upvote"
        },
        {
          "user": 2124,
          "type": "upvote"
        },
        {
          "user": 3911,
          "type": "upvote"
        },
        {
          "user": 253,
          "type": "upvote"
        },
        {
          "user": 2519,
          "type": "upvote"
        },
        {
          "user": 4272,
          "type": "upvote"
        },
        {
          "user": 3452,
          "type": "upvote"
        },
        {
          "user": 3274,
          "type": "upvote"
        },
        {
          "user": 3397,
          "type": "upvote"
        },
        {
          "user": 3514,
          "type": "upvote"
        },
        {
          "user": 3091,
          "type": "upvote"
        },
        {
          "user": 4547,
          "type": "upvote"
        },
        {
          "user": 2589,
          "type": "upvote"
        },
        {
          "user": 4524,
          "type": "upvote"
        },
        {
          "user": 3007,
          "type": "upvote"
        },
        {
          "user": 1606,
          "type": "upvote"
        },
        {
          "user": 1026,
          "type": "upvote"
        },
        {
          "user": 707,
          "type": "upvote"
        },
        {
          "user": 1007,
          "type": "upvote"
        },
        {
          "user": 2214,
          "type": "upvote"
        },
        {
          "user": 2043,
          "type": "upvote"
        },
        {
          "user": 3980,
          "type": "upvote"
        },
        {
          "user": 2306,
          "type": "upvote"
        },
        {
          "user": 497,
          "type": "upvote"
        },
        {
          "user": 1914,
          "type": "upvote"
        },
        {
          "user": 2942,
          "type": "upvote"
        },
        {
          "user": 4190,
          "type": "upvote"
        },
        {
          "user": 3766,
          "type": "upvote"
        },
        {
          "user": 4764,
          "type": "upvote"
        },
        {
          "user": 4807,
          "type": "upvote"
        },
        {
          "user": 2718,
          "type": "upvote"
        },
        {
          "user": 2688,
          "type": "upvote"
        },
        {
          "user": 4544,
          "type": "upvote"
        },
        {
          "user": 2143,
          "type": "upvote"
        },
        {
          "user": 785,
          "type": "upvote"
        },
        {
          "user": 3403,
          "type": "upvote"
        },
        {
          "user": 1568,
          "type": "upvote"
        },
        {
          "user": 952,
          "type": "upvote"
        },
        {
          "user": 2814,
          "type": "upvote"
        },
        {
          "user": 4620,
          "type": "upvote"
        },
        {
          "user": 511,
          "type": "upvote"
        },
        {
          "user": 1371,
          "type": "upvote"
        },
        {
          "user": 2036,
          "type": "upvote"
        },
        {
          "user": 1275,
          "type": "upvote"
        },
        {
          "user": 2293,
          "type": "upvote"
        },
        {
          "user": 4909,
          "type": "upvote"
        },
        {
          "user": 249,
          "type": "upvote"
        },
        {
          "user": 4135,
          "type": "upvote"
        },
        {
          "user": 2921,
          "type": "upvote"
        },
        {
          "user": 710,
          "type": "upvote"
        },
        {
          "user": 4579,
          "type": "upvote"
        },
        {
          "user": 119,
          "type": "upvote"
        },
        {
          "user": 4479,
          "type": "upvote"
        },
        {
          "user": 3225,
          "type": "upvote"
        },
        {
          "user": 3446,
          "type": "upvote"
        },
        {
          "user": 412,
          "type": "upvote"
        },
        {
          "user": 974,
          "type": "upvote"
        },
        {
          "user": 1106,
          "type": "upvote"
        },
        {
          "user": 2212,
          "type": "upvote"
        },
        {
          "user": 2592,
          "type": "upvote"
        },
        {
          "user": 20,
          "type": "upvote"
        },
        {
          "user": 823,
          "type": "upvote"
        },
        {
          "user": 743,
          "type": "upvote"
        },
        {
          "user": 2773,
          "type": "upvote"
        },
        {
          "user": 3661,
          "type": "upvote"
        },
        {
          "user": 544,
          "type": "upvote"
        },
        {
          "user": 3026,
          "type": "upvote"
        },
        {
          "user": 3501,
          "type": "upvote"
        },
        {
          "user": 2302,
          "type": "upvote"
        },
        {
          "user": 2966,
          "type": "upvote"
        },
        {
          "user": 1165,
          "type": "upvote"
        },
        {
          "user": 2569,
          "type": "upvote"
        },
        {
          "user": 4288,
          "type": "upvote"
        },
        {
          "user": 4360,
          "type": "upvote"
        },
        {
          "user": 4905,
          "type": "upvote"
        },
        {
          "user": 2684,
          "type": "upvote"
        },
        {
          "user": 3968,
          "type": "upvote"
        },
        {
          "user": 3285,
          "type": "upvote"
        },
        {
          "user": 4955,
          "type": "upvote"
        },
        {
          "user": 4354,
          "type": "upvote"
        },
        {
          "user": 160,
          "type": "upvote"
        },
        {
          "user": 2855,
          "type": "upvote"
        },
        {
          "user": 812,
          "type": "upvote"
        },
        {
          "user": 3979,
          "type": "upvote"
        },
        {
          "user": 3592,
          "type": "upvote"
        },
        {
          "user": 4092,
          "type": "upvote"
        },
        {
          "user": 2426,
          "type": "upvote"
        },
        {
          "user": 1506,
          "type": "upvote"
        },
        {
          "user": 4559,
          "type": "upvote"
        },
        {
          "user": 176,
          "type": "upvote"
        },
        {
          "user": 4892,
          "type": "upvote"
        },
        {
          "user": 4776,
          "type": "upvote"
        },
        {
          "user": 4862,
          "type": "upvote"
        },
        {
          "user": 1394,
          "type": "upvote"
        },
        {
          "user": 2929,
          "type": "upvote"
        },
        {
          "user": 2112,
          "type": "upvote"
        },
        {
          "user": 580,
          "type": "upvote"
        },
        {
          "user": 2215,
          "type": "upvote"
        },
        {
          "user": 1478,
          "type": "upvote"
        },
        {
          "user": 3417,
          "type": "upvote"
        },
        {
          "user": 793,
          "type": "upvote"
        },
        {
          "user": 4357,
          "type": "upvote"
        },
        {
          "user": 428,
          "type": "upvote"
        },
        {
          "user": 465,
          "type": "upvote"
        },
        {
          "user": 3680,
          "type": "upvote"
        },
        {
          "user": 1567,
          "type": "upvote"
        },
        {
          "user": 4139,
          "type": "upvote"
        },
        {
          "user": 2815,
          "type": "upvote"
        },
        {
          "user": 381,
          "type": "upvote"
        },
        {
          "user": 4906,
          "type": "upvote"
        },
        {
          "user": 809,
          "type": "upvote"
        },
        {
          "user": 1790,
          "type": "upvote"
        },
        {
          "user": 4407,
          "type": "upvote"
        },
        {
          "user": 4191,
          "type": "upvote"
        },
        {
          "user": 3011,
          "type": "upvote"
        },
        {
          "user": 4518,
          "type": "upvote"
        },
        {
          "user": 1048,
          "type": "upvote"
        },
        {
          "user": 2422,
          "type": "upvote"
        },
        {
          "user": 4482,
          "type": "upvote"
        },
        {
          "user": 4217,
          "type": "upvote"
        },
        {
          "user": 502,
          "type": "upvote"
        },
        {
          "user": 3880,
          "type": "upvote"
        },
        {
          "user": 3598,
          "type": "upvote"
        },
        {
          "user": 4946,
          "type": "upvote"
        },
        {
          "user": 4780,
          "type": "upvote"
        },
        {
          "user": 3649,
          "type": "upvote"
        },
        {
          "user": 2422,
          "type": "upvote"
        },
        {
          "user": 4830,
          "type": "upvote"
        },
        {
          "user": 1768,
          "type": "upvote"
        },
        {
          "user": 285,
          "type": "upvote"
        },
        {
          "user": 4901,
          "type": "upvote"
        },
        {
          "user": 4794,
          "type": "upvote"
        },
        {
          "user": 2900,
          "type": "upvote"
        },
        {
          "user": 1902,
          "type": "upvote"
        },
        {
          "user": 84,
          "type": "upvote"
        },
        {
          "user": 2929,
          "type": "upvote"
        },
        {
          "user": 1814,
          "type": "upvote"
        },
        {
          "user": 2867,
          "type": "upvote"
        },
        {
          "user": 3776,
          "type": "upvote"
        },
        {
          "user": 3987,
          "type": "upvote"
        },
        {
          "user": 966,
          "type": "upvote"
        },
        {
          "user": 681,
          "type": "upvote"
        },
        {
          "user": 4638,
          "type": "upvote"
        },
        {
          "user": 3,
          "type": "upvote"
        },
        {
          "user": 540,
          "type": "upvote"
        },
        {
          "user": 2875,
          "type": "upvote"
        },
        {
          "user": 235,
          "type": "upvote"
        },
        {
          "user": 4920,
          "type": "upvote"
        },
        {
          "user": 1432,
          "type": "upvote"
        },
        {
          "user": 1807,
          "type": "upvote"
        },
        {
          "user": 2694,
          "type": "upvote"
        },
        {
          "user": 214,
          "type": "upvote"
        },
        {
          "user": 1616,
          "type": "upvote"
        },
        {
          "user": 3040,
          "type": "upvote"
        },
        {
          "user": 3979,
          "type": "upvote"
        },
        {
          "user": 4634,
          "type": "upvote"
        },
        {
          "user": 4676,
          "type": "upvote"
        },
        {
          "user": 4940,
          "type": "upvote"
        },
        {
          "user": 252,
          "type": "upvote"
        },
        {
          "user": 4538,
          "type": "upvote"
        },
        {
          "user": 1735,
          "type": "upvote"
        },
        {
          "user": 2686,
          "type": "upvote"
        },
        {
          "user": 669,
          "type": "upvote"
        },
        {
          "user": 1850,
          "type": "upvote"
        },
        {
          "user": 1311,
          "type": "upvote"
        },
        {
          "user": 1522,
          "type": "upvote"
        },
        {
          "user": 1812,
          "type": "upvote"
        },
        {
          "user": 1722,
          "type": "upvote"
        },
        {
          "user": 245,
          "type": "upvote"
        },
        {
          "user": 4589,
          "type": "upvote"
        },
        {
          "user": 483,
          "type": "upvote"
        },
        {
          "user": 980,
          "type": "upvote"
        },
        {
          "user": 2910,
          "type": "upvote"
        },
        {
          "user": 606,
          "type": "upvote"
        },
        {
          "user": 2395,
          "type": "upvote"
        },
        {
          "user": 4596,
          "type": "upvote"
        },
        {
          "user": 4523,
          "type": "upvote"
        },
        {
          "user": 3220,
          "type": "upvote"
        },
        {
          "user": 248,
          "type": "upvote"
        },
        {
          "user": 4963,
          "type": "upvote"
        },
        {
          "user": 3094,
          "type": "upvote"
        },
        {
          "user": 3930,
          "type": "upvote"
        },
        {
          "user": 47,
          "type": "upvote"
        },
        {
          "user": 998,
          "type": "upvote"
        },
        {
          "user": 4181,
          "type": "upvote"
        },
        {
          "user": 3881,
          "type": "upvote"
        },
        {
          "user": 3166,
          "type": "upvote"
        },
        {
          "user": 1322,
          "type": "upvote"
        },
        {
          "user": 1196,
          "type": "upvote"
        },
        {
          "user": 1342,
          "type": "upvote"
        },
        {
          "user": 2492,
          "type": "upvote"
        },
        {
          "user": 1434,
          "type": "upvote"
        },
        {
          "user": 3671,
          "type": "upvote"
        },
        {
          "user": 137,
          "type": "upvote"
        },
        {
          "user": 2539,
          "type": "upvote"
        },
        {
          "user": 2967,
          "type": "upvote"
        },
        {
          "user": 998,
          "type": "upvote"
        },
        {
          "user": 3744,
          "type": "upvote"
        },
        {
          "user": 2238,
          "type": "upvote"
        },
        {
          "user": 4770,
          "type": "upvote"
        },
        {
          "user": 4253,
          "type": "upvote"
        },
        {
          "user": 4180,
          "type": "upvote"
        },
        {
          "user": 2569,
          "type": "upvote"
        },
        {
          "user": 899,
          "type": "upvote"
        },
        {
          "user": 540,
          "type": "upvote"
        },
        {
          "user": 2943,
          "type": "upvote"
        },
        {
          "user": 1499,
          "type": "upvote"
        },
        {
          "user": 2480,
          "type": "upvote"
        },
        {
          "user": 3906,
          "type": "upvote"
        },
        {
          "user": 1172,
          "type": "upvote"
        },
        {
          "user": 1988,
          "type": "upvote"
        },
        {
          "user": 2102,
          "type": "upvote"
        },
        {
          "user": 2175,
          "type": "upvote"
        },
        {
          "user": 3958,
          "type": "upvote"
        },
        {
          "user": 153,
          "type": "upvote"
        },
        {
          "user": 1220,
          "type": "upvote"
        },
        {
          "user": 2167,
          "type": "upvote"
        },
        {
          "user": 3123,
          "type": "upvote"
        },
        {
          "user": 1065,
          "type": "upvote"
        },
        {
          "user": 3101,
          "type": "upvote"
        },
        {
          "user": 1737,
          "type": "upvote"
        },
        {
          "user": 3886,
          "type": "upvote"
        },
        {
          "user": 4460,
          "type": "upvote"
        },
        {
          "user": 1926,
          "type": "upvote"
        },
        {
          "user": 2856,
          "type": "upvote"
        },
        {
          "user": 443,
          "type": "upvote"
        },
        {
          "user": 801,
          "type": "upvote"
        },
        {
          "user": 1459,
          "type": "upvote"
        },
        {
          "user": 3931,
          "type": "upvote"
        },
        {
          "user": 4302,
          "type": "upvote"
        },
        {
          "user": 4045,
          "type": "upvote"
        },
        {
          "user": 1403,
          "type": "upvote"
        },
        {
          "user": 2386,
          "type": "upvote"
        },
        {
          "user": 1678,
          "type": "upvote"
        },
        {
          "user": 2267,
          "type": "upvote"
        },
        {
          "user": 3551,
          "type": "upvote"
        },
        {
          "user": 3974,
          "type": "upvote"
        },
        {
          "user": 4972,
          "type": "upvote"
        },
        {
          "user": 3772,
          "type": "upvote"
        },
        {
          "user": 1532,
          "type": "upvote"
        },
        {
          "user": 4903,
          "type": "upvote"
        },
        {
          "user": 2995,
          "type": "upvote"
        },
        {
          "user": 673,
          "type": "upvote"
        },
        {
          "user": 3171,
          "type": "upvote"
        },
        {
          "user": 4986,
          "type": "upvote"
        },
        {
          "user": 3512,
          "type": "upvote"
        },
        {
          "user": 3603,
          "type": "upvote"
        },
        {
          "user": 3753,
          "type": "upvote"
        },
        {
          "user": 2619,
          "type": "upvote"
        },
        {
          "user": 3972,
          "type": "upvote"
        },
        {
          "user": 1250,
          "type": "upvote"
        },
        {
          "user": 3334,
          "type": "upvote"
        },
        {
          "user": 1302,
          "type": "upvote"
        },
        {
          "user": 885,
          "type": "upvote"
        },
        {
          "user": 2152,
          "type": "upvote"
        },
        {
          "user": 4731,
          "type": "upvote"
        },
        {
          "user": 3150,
          "type": "upvote"
        },
        {
          "user": 2511,
          "type": "upvote"
        },
        {
          "user": 3659,
          "type": "upvote"
        },
        {
          "user": 2951,
          "type": "upvote"
        },
        {
          "user": 2163,
          "type": "upvote"
        },
        {
          "user": 2203,
          "type": "upvote"
        },
        {
          "user": 1024,
          "type": "upvote"
        },
        {
          "user": 1386,
          "type": "upvote"
        },
        {
          "user": 1388,
          "type": "upvote"
        },
        {
          "user": 4895,
          "type": "upvote"
        },
        {
          "user": 1415,
          "type": "upvote"
        },
        {
          "user": 2192,
          "type": "upvote"
        },
        {
          "user": 2932,
          "type": "upvote"
        },
        {
          "user": 2583,
          "type": "upvote"
        },
        {
          "user": 4024,
          "type": "upvote"
        },
        {
          "user": 472,
          "type": "upvote"
        },
        {
          "user": 2828,
          "type": "upvote"
        },
        {
          "user": 3698,
          "type": "upvote"
        },
        {
          "user": 3264,
          "type": "upvote"
        },
        {
          "user": 4652,
          "type": "upvote"
        },
        {
          "user": 1499,
          "type": "upvote"
        },
        {
          "user": 1960,
          "type": "upvote"
        },
        {
          "user": 3432,
          "type": "upvote"
        },
        {
          "user": 910,
          "type": "upvote"
        },
        {
          "user": 3210,
          "type": "upvote"
        },
        {
          "user": 2313,
          "type": "upvote"
        },
        {
          "user": 2123,
          "type": "upvote"
        },
        {
          "user": 4954,
          "type": "upvote"
        },
        {
          "user": 449,
          "type": "upvote"
        },
        {
          "user": 1877,
          "type": "upvote"
        },
        {
          "user": 3190,
          "type": "upvote"
        },
        {
          "user": 3777,
          "type": "upvote"
        },
        {
          "user": 4333,
          "type": "upvote"
        },
        {
          "user": 3848,
          "type": "upvote"
        },
        {
          "user": 612,
          "type": "upvote"
        },
        {
          "user": 2196,
          "type": "upvote"
        },
        {
          "user": 3877,
          "type": "upvote"
        },
        {
          "user": 376,
          "type": "upvote"
        },
        {
          "user": 4318,
          "type": "upvote"
        },
        {
          "user": 492,
          "type": "upvote"
        },
        {
          "user": 1474,
          "type": "upvote"
        },
        {
          "user": 1915,
          "type": "upvote"
        },
        {
          "user": 772,
          "type": "upvote"
        },
        {
          "user": 3720,
          "type": "upvote"
        },
        {
          "user": 1346,
          "type": "upvote"
        },
        {
          "user": 2386,
          "type": "upvote"
        },
        {
          "user": 3900,
          "type": "upvote"
        },
        {
          "user": 4655,
          "type": "upvote"
        },
        {
          "user": 2458,
          "type": "upvote"
        },
        {
          "user": 4530,
          "type": "upvote"
        },
        {
          "user": 713,
          "type": "upvote"
        },
        {
          "user": 2204,
          "type": "upvote"
        },
        {
          "user": 3004,
          "type": "upvote"
        },
        {
          "user": 3817,
          "type": "upvote"
        },
        {
          "user": 732,
          "type": "upvote"
        },
        {
          "user": 2199,
          "type": "upvote"
        },
        {
          "user": 4180,
          "type": "upvote"
        },
        {
          "user": 346,
          "type": "upvote"
        },
        {
          "user": 2829,
          "type": "upvote"
        },
        {
          "user": 18,
          "type": "upvote"
        },
        {
          "user": 3166,
          "type": "upvote"
        },
        {
          "user": 1452,
          "type": "upvote"
        },
        {
          "user": 3046,
          "type": "upvote"
        },
        {
          "user": 2979,
          "type": "upvote"
        },
        {
          "user": 884,
          "type": "upvote"
        },
        {
          "user": 4177,
          "type": "upvote"
        },
        {
          "user": 1253,
          "type": "upvote"
        },
        {
          "user": 967,
          "type": "upvote"
        },
        {
          "user": 4792,
          "type": "upvote"
        },
        {
          "user": 2063,
          "type": "upvote"
        },
        {
          "user": 383,
          "type": "upvote"
        },
        {
          "user": 849,
          "type": "upvote"
        },
        {
          "user": 1938,
          "type": "upvote"
        },
        {
          "user": 1323,
          "type": "upvote"
        },
        {
          "user": 2182,
          "type": "upvote"
        },
        {
          "user": 2131,
          "type": "upvote"
        },
        {
          "user": 1564,
          "type": "upvote"
        },
        {
          "user": 4099,
          "type": "upvote"
        },
        {
          "user": 1483,
          "type": "upvote"
        },
        {
          "user": 1596,
          "type": "upvote"
        },
        {
          "user": 2122,
          "type": "upvote"
        },
        {
          "user": 2197,
          "type": "upvote"
        },
        {
          "user": 3040,
          "type": "upvote"
        },
        {
          "user": 471,
          "type": "upvote"
        },
        {
          "user": 616,
          "type": "upvote"
        },
        {
          "user": 4551,
          "type": "upvote"
        },
        {
          "user": 1484,
          "type": "upvote"
        },
        {
          "user": 3308,
          "type": "upvote"
        },
        {
          "user": 4673,
          "type": "upvote"
        },
        {
          "user": 1636,
          "type": "upvote"
        },
        {
          "user": 4116,
          "type": "upvote"
        },
        {
          "user": 404,
          "type": "upvote"
        },
        {
          "user": 2560,
          "type": "upvote"
        },
        {
          "user": 2661,
          "type": "upvote"
        },
        {
          "user": 411,
          "type": "upvote"
        },
        {
          "user": 2785,
          "type": "upvote"
        },
        {
          "user": 4388,
          "type": "upvote"
        },
        {
          "user": 2537,
          "type": "upvote"
        },
        {
          "user": 1105,
          "type": "upvote"
        },
        {
          "user": 4142,
          "type": "upvote"
        },
        {
          "user": 543,
          "type": "upvote"
        },
        {
          "user": 2759,
          "type": "upvote"
        },
        {
          "user": 4402,
          "type": "upvote"
        },
        {
          "user": 1397,
          "type": "upvote"
        },
        {
          "user": 431,
          "type": "upvote"
        },
        {
          "user": 1297,
          "type": "upvote"
        },
        {
          "user": 3967,
          "type": "upvote"
        },
        {
          "user": 4407,
          "type": "upvote"
        },
        {
          "user": 2965,
          "type": "upvote"
        },
        {
          "user": 700,
          "type": "upvote"
        },
        {
          "user": 4114,
          "type": "upvote"
        },
        {
          "user": 4792,
          "type": "upvote"
        },
        {
          "user": 3316,
          "type": "upvote"
        },
        {
          "user": 1530,
          "type": "upvote"
        },
        {
          "user": 3779,
          "type": "upvote"
        },
        {
          "user": 2110,
          "type": "upvote"
        },
        {
          "user": 2648,
          "type": "upvote"
        },
        {
          "user": 3585,
          "type": "upvote"
        },
        {
          "user": 2178,
          "type": "upvote"
        },
        {
          "user": 3524,
          "type": "upvote"
        },
        {
          "user": 2417,
          "type": "upvote"
        },
        {
          "user": 3933,
          "type": "upvote"
        },
        {
          "user": 3135,
          "type": "upvote"
        },
        {
          "user": 1744,
          "type": "upvote"
        },
        {
          "user": 3516,
          "type": "upvote"
        },
        {
          "user": 4551,
          "type": "upvote"
        },
        {
          "user": 3650,
          "type": "upvote"
        },
        {
          "user": 1725,
          "type": "upvote"
        },
        {
          "user": 2922,
          "type": "upvote"
        },
        {
          "user": 41,
          "type": "upvote"
        },
        {
          "user": 3513,
          "type": "upvote"
        },
        {
          "user": 1861,
          "type": "upvote"
        },
        {
          "user": 4322,
          "type": "upvote"
        },
        {
          "user": 4656,
          "type": "upvote"
        },
        {
          "user": 2090,
          "type": "upvote"
        },
        {
          "user": 340,
          "type": "upvote"
        },
        {
          "user": 3961,
          "type": "upvote"
        },
        {
          "user": 4577,
          "type": "upvote"
        },
        {
          "user": 2276,
          "type": "upvote"
        },
        {
          "user": 3040,
          "type": "upvote"
        },
        {
          "user": 1542,
          "type": "upvote"
        },
        {
          "user": 4792,
          "type": "upvote"
        },
        {
          "user": 2380,
          "type": "upvote"
        },
        {
          "user": 3161,
          "type": "upvote"
        },
        {
          "user": 771,
          "type": "upvote"
        },
        {
          "user": 2379,
          "type": "upvote"
        },
        {
          "user": 1842,
          "type": "upvote"
        },
        {
          "user": 2867,
          "type": "upvote"
        },
        {
          "user": 2937,
          "type": "upvote"
        },
        {
          "user": 4079,
          "type": "upvote"
        },
        {
          "user": 2688,
          "type": "upvote"
        },
        {
          "user": 4072,
          "type": "upvote"
        },
        {
          "user": 3014,
          "type": "upvote"
        },
        {
          "user": 3178,
          "type": "upvote"
        },
        {
          "user": 2615,
          "type": "upvote"
        },
        {
          "user": 685,
          "type": "upvote"
        },
        {
          "user": 1589,
          "type": "upvote"
        },
        {
          "user": 4170,
          "type": "upvote"
        },
        {
          "user": 1918,
          "type": "upvote"
        },
        {
          "user": 3542,
          "type": "upvote"
        },
        {
          "user": 515,
          "type": "upvote"
        },
        {
          "user": 1337,
          "type": "upvote"
        },
        {
          "user": 3670,
          "type": "upvote"
        },
        {
          "user": 2377,
          "type": "upvote"
        },
        {
          "user": 456,
          "type": "upvote"
        },
        {
          "user": 2603,
          "type": "upvote"
        },
        {
          "user": 2802,
          "type": "upvote"
        },
        {
          "user": 3719,
          "type": "upvote"
        },
        {
          "user": 4285,
          "type": "upvote"
        },
        {
          "user": 3079,
          "type": "upvote"
        },
        {
          "user": 3352,
          "type": "upvote"
        },
        {
          "user": 4083,
          "type": "upvote"
        },
        {
          "user": 2002,
          "type": "upvote"
        },
        {
          "user": 3520,
          "type": "upvote"
        },
        {
          "user": 4844,
          "type": "upvote"
        },
        {
          "user": 2656,
          "type": "upvote"
        },
        {
          "user": 85,
          "type": "upvote"
        },
        {
          "user": 319,
          "type": "upvote"
        },
        {
          "user": 1042,
          "type": "upvote"
        },
        {
          "user": 821,
          "type": "upvote"
        },
        {
          "user": 4054,
          "type": "upvote"
        },
        {
          "user": 4823,
          "type": "upvote"
        },
        {
          "user": 2657,
          "type": "upvote"
        },
        {
          "user": 3207,
          "type": "upvote"
        },
        {
          "user": 2131,
          "type": "upvote"
        },
        {
          "user": 1521,
          "type": "upvote"
        },
        {
          "user": 4194,
          "type": "upvote"
        },
        {
          "user": 1238,
          "type": "upvote"
        },
        {
          "user": 3995,
          "type": "upvote"
        },
        {
          "user": 4905,
          "type": "upvote"
        },
        {
          "user": 2559,
          "type": "upvote"
        },
        {
          "user": 1710,
          "type": "upvote"
        },
        {
          "user": 2550,
          "type": "upvote"
        },
        {
          "user": 3002,
          "type": "upvote"
        },
        {
          "user": 3166,
          "type": "upvote"
        },
        {
          "user": 1319,
          "type": "upvote"
        },
        {
          "user": 2322,
          "type": "upvote"
        },
        {
          "user": 3397,
          "type": "upvote"
        },
        {
          "user": 772,
          "type": "upvote"
        },
        {
          "user": 84,
          "type": "upvote"
        },
        {
          "user": 2015,
          "type": "upvote"
        },
        {
          "user": 4724,
          "type": "upvote"
        },
        {
          "user": 1651,
          "type": "upvote"
        },
        {
          "user": 730,
          "type": "upvote"
        },
        {
          "user": 1536,
          "type": "upvote"
        },
        {
          "user": 930,
          "type": "upvote"
        },
        {
          "user": 4663,
          "type": "upvote"
        },
        {
          "user": 1326,
          "type": "upvote"
        },
        {
          "user": 163,
          "type": "upvote"
        },
        {
          "user": 3787,
          "type": "upvote"
        },
        {
          "user": 4872,
          "type": "upvote"
        },
        {
          "user": 342,
          "type": "upvote"
        },
        {
          "user": 4486,
          "type": "upvote"
        },
        {
          "user": 407,
          "type": "upvote"
        },
        {
          "user": 2992,
          "type": "upvote"
        },
        {
          "user": 1160,
          "type": "upvote"
        },
        {
          "user": 1832,
          "type": "upvote"
        },
        {
          "user": 1667,
          "type": "upvote"
        },
        {
          "user": 1115,
          "type": "upvote"
        },
        {
          "user": 3077,
          "type": "upvote"
        },
        {
          "user": 3226,
          "type": "upvote"
        },
        {
          "user": 4376,
          "type": "upvote"
        },
        {
          "user": 3192,
          "type": "upvote"
        },
        {
          "user": 3117,
          "type": "upvote"
        },
        {
          "user": 1176,
          "type": "upvote"
        },
        {
          "user": 3404,
          "type": "upvote"
        },
        {
          "user": 47,
          "type": "upvote"
        },
        {
          "user": 3869,
          "type": "upvote"
        },
        {
          "user": 2439,
          "type": "upvote"
        },
        {
          "user": 3895,
          "type": "upvote"
        },
        {
          "user": 3229,
          "type": "upvote"
        },
        {
          "user": 3486,
          "type": "upvote"
        },
        {
          "user": 326,
          "type": "upvote"
        },
        {
          "user": 1042,
          "type": "upvote"
        },
        {
          "user": 1744,
          "type": "upvote"
        },
        {
          "user": 355,
          "type": "upvote"
        },
        {
          "user": 876,
          "type": "upvote"
        },
        {
          "user": 655,
          "type": "upvote"
        },
        {
          "user": 1397,
          "type": "upvote"
        },
        {
          "user": 2278,
          "type": "upvote"
        },
        {
          "user": 4121,
          "type": "upvote"
        },
        {
          "user": 2953,
          "type": "upvote"
        },
        {
          "user": 3518,
          "type": "upvote"
        },
        {
          "user": 3642,
          "type": "upvote"
        },
        {
          "user": 3426,
          "type": "upvote"
        },
        {
          "user": 2406,
          "type": "upvote"
        },
        {
          "user": 3896,
          "type": "upvote"
        },
        {
          "user": 1379,
          "type": "upvote"
        },
        {
          "user": 2359,
          "type": "upvote"
        },
        {
          "user": 3015,
          "type": "upvote"
        },
        {
          "user": 2780,
          "type": "upvote"
        },
        {
          "user": 1160,
          "type": "upvote"
        },
        {
          "user": 1239,
          "type": "upvote"
        },
        {
          "user": 3020,
          "type": "upvote"
        },
        {
          "user": 527,
          "type": "upvote"
        },
        {
          "user": 930,
          "type": "upvote"
        },
        {
          "user": 36,
          "type": "upvote"
        },
        {
          "user": 3929,
          "type": "upvote"
        },
        {
          "user": 1157,
          "type": "upvote"
        },
        {
          "user": 1680,
          "type": "upvote"
        },
        {
          "user": 2296,
          "type": "upvote"
        },
        {
          "user": 4340,
          "type": "upvote"
        },
        {
          "user": 3177,
          "type": "upvote"
        },
        {
          "user": 1295,
          "type": "upvote"
        },
        {
          "user": 2750,
          "type": "upvote"
        },
        {
          "user": 1371,
          "type": "upvote"
        },
        {
          "user": 1174,
          "type": "upvote"
        },
        {
          "user": 4463,
          "type": "upvote"
        },
        {
          "user": 4618,
          "type": "upvote"
        },
        {
          "user": 169,
          "type": "upvote"
        },
        {
          "user": 4269,
          "type": "upvote"
        },
        {
          "user": 2853,
          "type": "upvote"
        },
        {
          "user": 4336,
          "type": "upvote"
        },
        {
          "user": 3975,
          "type": "upvote"
        },
        {
          "user": 1524,
          "type": "upvote"
        },
        {
          "user": 4095,
          "type": "upvote"
        },
        {
          "user": 2467,
          "type": "upvote"
        },
        {
          "user": 3314,
          "type": "upvote"
        },
        {
          "user": 1173,
          "type": "upvote"
        },
        {
          "user": 4335,
          "type": "upvote"
        },
        {
          "user": 3503,
          "type": "upvote"
        },
        {
          "user": 4978,
          "type": "upvote"
        },
        {
          "user": 1896,
          "type": "upvote"
        },
        {
          "user": 890,
          "type": "upvote"
        },
        {
          "user": 2734,
          "type": "upvote"
        },
        {
          "user": 4103,
          "type": "upvote"
        },
        {
          "user": 2593,
          "type": "upvote"
        },
        {
          "user": 292,
          "type": "upvote"
        },
        {
          "user": 416,
          "type": "upvote"
        },
        {
          "user": 2908,
          "type": "upvote"
        },
        {
          "user": 4601,
          "type": "upvote"
        },
        {
          "user": 2131,
          "type": "upvote"
        },
        {
          "user": 4417,
          "type": "upvote"
        },
        {
          "user": 1015,
          "type": "upvote"
        },
        {
          "user": 3818,
          "type": "upvote"
        },
        {
          "user": 2684,
          "type": "upvote"
        },
        {
          "user": 2398,
          "type": "upvote"
        },
        {
          "user": 3540,
          "type": "upvote"
        },
        {
          "user": 3792,
          "type": "upvote"
        },
        {
          "user": 4870,
          "type": "upvote"
        },
        {
          "user": 2935,
          "type": "upvote"
        },
        {
          "user": 3130,
          "type": "upvote"
        },
        {
          "user": 947,
          "type": "upvote"
        },
        {
          "user": 664,
          "type": "upvote"
        },
        {
          "user": 4442,
          "type": "upvote"
        },
        {
          "user": 2617,
          "type": "upvote"
        },
        {
          "user": 1130,
          "type": "upvote"
        },
        {
          "user": 1319,
          "type": "upvote"
        },
        {
          "user": 3432,
          "type": "upvote"
        },
        {
          "user": 514,
          "type": "upvote"
        },
        {
          "user": 4419,
          "type": "upvote"
        },
        {
          "user": 419,
          "type": "upvote"
        },
        {
          "user": 2072,
          "type": "upvote"
        },
        {
          "user": 1616,
          "type": "upvote"
        },
        {
          "user": 3689,
          "type": "upvote"
        },
        {
          "user": 2136,
          "type": "upvote"
        },
        {
          "user": 2456,
          "type": "upvote"
        },
        {
          "user": 4662,
          "type": "upvote"
        },
        {
          "user": 4717,
          "type": "upvote"
        },
        {
          "user": 3662,
          "type": "upvote"
        },
        {
          "user": 3763,
          "type": "upvote"
        },
        {
          "user": 4922,
          "type": "upvote"
        },
        {
          "user": 360,
          "type": "upvote"
        },
        {
          "user": 646,
          "type": "upvote"
        },
        {
          "user": 122,
          "type": "upvote"
        },
        {
          "user": 742,
          "type": "upvote"
        },
        {
          "user": 2861,
          "type": "upvote"
        },
        {
          "user": 3845,
          "type": "upvote"
        },
        {
          "user": 817,
          "type": "upvote"
        },
        {
          "user": 3413,
          "type": "upvote"
        },
        {
          "user": 4012,
          "type": "upvote"
        },
        {
          "user": 1928,
          "type": "upvote"
        },
        {
          "user": 4657,
          "type": "upvote"
        },
        {
          "user": 394,
          "type": "upvote"
        },
        {
          "user": 1604,
          "type": "upvote"
        },
        {
          "user": 515,
          "type": "upvote"
        },
        {
          "user": 3214,
          "type": "upvote"
        },
        {
          "user": 4727,
          "type": "upvote"
        },
        {
          "user": 887,
          "type": "upvote"
        },
        {
          "user": 2664,
          "type": "upvote"
        },
        {
          "user": 4054,
          "type": "upvote"
        },
        {
          "user": 431,
          "type": "upvote"
        },
        {
          "user": 4293,
          "type": "upvote"
        },
        {
          "user": 2364,
          "type": "upvote"
        },
        {
          "user": 2501,
          "type": "upvote"
        },
        {
          "user": 295,
          "type": "upvote"
        },
        {
          "user": 784,
          "type": "upvote"
        },
        {
          "user": 2982,
          "type": "upvote"
        },
        {
          "user": 446,
          "type": "upvote"
        },
        {
          "user": 1715,
          "type": "upvote"
        },
        {
          "user": 734,
          "type": "upvote"
        },
        {
          "user": 1119,
          "type": "upvote"
        },
        {
          "user": 4313,
          "type": "upvote"
        },
        {
          "user": 4417,
          "type": "upvote"
        },
        {
          "user": 1248,
          "type": "upvote"
        },
        {
          "user": 4260,
          "type": "upvote"
        },
        {
          "user": 4837,
          "type": "upvote"
        },
        {
          "user": 841,
          "type": "upvote"
        },
        {
          "user": 3168,
          "type": "upvote"
        },
        {
          "user": 1129,
          "type": "upvote"
        },
        {
          "user": 4383,
          "type": "upvote"
        },
        {
          "user": 4514,
          "type": "upvote"
        },
        {
          "user": 1350,
          "type": "upvote"
        },
        {
          "user": 788,
          "type": "upvote"
        },
        {
          "user": 1029,
          "type": "upvote"
        },
        {
          "user": 198,
          "type": "upvote"
        },
        {
          "user": 3245,
          "type": "upvote"
        },
        {
          "user": 3084,
          "type": "upvote"
        },
        {
          "user": 237,
          "type": "upvote"
        },
        {
          "user": 725,
          "type": "upvote"
        },
        {
          "user": 3272,
          "type": "upvote"
        },
        {
          "user": 1570,
          "type": "upvote"
        },
        {
          "user": 4719,
          "type": "upvote"
        },
        {
          "user": 2484,
          "type": "upvote"
        },
        {
          "user": 2173,
          "type": "upvote"
        },
        {
          "user": 1118,
          "type": "upvote"
        },
        {
          "user": 234,
          "type": "upvote"
        },
        {
          "user": 1061,
          "type": "upvote"
        },
        {
          "user": 149,
          "type": "upvote"
        },
        {
          "user": 438,
          "type": "upvote"
        },
        {
          "user": 3501,
          "type": "upvote"
        },
        {
          "user": 1019,
          "type": "upvote"
        },
        {
          "user": 4722,
          "type": "upvote"
        },
        {
          "user": 4643,
          "type": "upvote"
        },
        {
          "user": 459,
          "type": "downvote"
        },
        {
          "user": 2930,
          "type": "downvote"
        },
        {
          "user": 2890,
          "type": "downvote"
        },
        {
          "user": 3326,
          "type": "downvote"
        },
        {
          "user": 4753,
          "type": "downvote"
        },
        {
          "user": 63,
          "type": "downvote"
        },
        {
          "user": 2282,
          "type": "downvote"
        },
        {
          "user": 2912,
          "type": "downvote"
        },
        {
          "user": 4232,
          "type": "downvote"
        },
        {
          "user": 2183,
          "type": "downvote"
        },
        {
          "user": 4591,
          "type": "downvote"
        },
        {
          "user": 3658,
          "type": "downvote"
        },
        {
          "user": 2093,
          "type": "downvote"
        },
        {
          "user": 2919,
          "type": "downvote"
        },
        {
          "user": 677,
          "type": "downvote"
        },
        {
          "user": 2233,
          "type": "downvote"
        },
        {
          "user": 867,
          "type": "downvote"
        },
        {
          "user": 3637,
          "type": "downvote"
        },
        {
          "user": 216,
          "type": "downvote"
        },
        {
          "user": 3608,
          "type": "downvote"
        },
        {
          "user": 1315,
          "type": "downvote"
        },
        {
          "user": 1748,
          "type": "downvote"
        },
        {
          "user": 582,
          "type": "downvote"
        },
        {
          "user": 1286,
          "type": "downvote"
        },
        {
          "user": 3951,
          "type": "downvote"
        },
        {
          "user": 702,
          "type": "downvote"
        },
        {
          "user": 1747,
          "type": "downvote"
        },
        {
          "user": 2850,
          "type": "downvote"
        },
        {
          "user": 2746,
          "type": "downvote"
        },
        {
          "user": 3799,
          "type": "downvote"
        },
        {
          "user": 4603,
          "type": "downvote"
        },
        {
          "user": 2640,
          "type": "downvote"
        },
        {
          "user": 3313,
          "type": "downvote"
        },
        {
          "user": 2291,
          "type": "downvote"
        },
        {
          "user": 4689,
          "type": "downvote"
        },
        {
          "user": 3660,
          "type": "downvote"
        },
        {
          "user": 2311,
          "type": "downvote"
        },
        {
          "user": 1597,
          "type": "downvote"
        },
        {
          "user": 601,
          "type": "downvote"
        },
        {
          "user": 634,
          "type": "downvote"
        },
        {
          "user": 4694,
          "type": "downvote"
        },
        {
          "user": 4088,
          "type": "downvote"
        },
        {
          "user": 4593,
          "type": "downvote"
        },
        {
          "user": 2766,
          "type": "downvote"
        },
        {
          "user": 3955,
          "type": "downvote"
        },
        {
          "user": 4364,
          "type": "downvote"
        },
        {
          "user": 4415,
          "type": "downvote"
        },
        {
          "user": 2357,
          "type": "downvote"
        },
        {
          "user": 329,
          "type": "downvote"
        },
        {
          "user": 76,
          "type": "downvote"
        },
        {
          "user": 1277,
          "type": "downvote"
        },
        {
          "user": 4295,
          "type": "downvote"
        },
        {
          "user": 2384,
          "type": "downvote"
        },
        {
          "user": 4243,
          "type": "downvote"
        },
        {
          "user": 3186,
          "type": "downvote"
        },
        {
          "user": 2631,
          "type": "downvote"
        },
        {
          "user": 557,
          "type": "downvote"
        },
        {
          "user": 3288,
          "type": "downvote"
        },
        {
          "user": 3043,
          "type": "downvote"
        },
        {
          "user": 480,
          "type": "downvote"
        }
      ]
    }
  ],
  "comments": [
    {
      "id": 1,
      "text": "a comment about post 1",
      "postId": 1,
      "userId": 4279,
      "comments": [
        {
          "id": 3,
          "text": "a reply to the first comment",
          "postId": 1,
          "userId": 1595
        }
      ]
    },
    {
      "id": 2,
      "text": "another comment about post 1",
      "postId": 1,
      "userId": 1595
    }
  ],
  "users": {
    "id": "0",
    "username": "admin",
    "password": "$2a$12$PlEcK.X4jENxXQrT7F9.tut6qdaXCCgcrV4y5X7jk7gwBWWD2S3bi",
    "role": "admin",
    "firstname": "Trust Me",
    "lastname": "Bro",
    "email": "admin@gmail.com",
    "phone": "123-456-7890",
    "address": {
      "street": "123 Main St",
      "city": "Anytown",
      "state": "CA",
      "zip": "12345"
    },
    "bookmarks": [
      1,
      3
    ]
  }
}